dbgenie/__init__.py
dbgenie/mongodb/__init__.py
dbgenie/mongodb/mongocrud.py
dbgenie/mysql/__init__.py
dbgenie/mysql/mysqlcrud.py
dbgenie/postgresql/__init__.py
dbgenie/postgresql/postgrescrud.py
dbgenie2-0.0.1.dist-info/METADATA
dbgenie2-0.0.1.dist-info/WHEEL
dbgenie2-0.0.1.dist-info/top_level.txt
dbgenie2-0.0.1.dist-info/RECORD
