Metadata-Version: 2.1
Name: dbgenie2
Version: 0.0.1
Summary: A python package for automating database operations.
Home-page: https://github.com/hrshankar2002/DBGenie
Author: hrshankar2002
Author-email: hrshankar2002@gmail.com
License: MIT
Project-URL: Bug Tracker, https://github.com/hrshankar2002/DBGenie/issues
Classifier: Programming Language :: Python :: 3.7
Classifier: Programming Language :: Python :: 3.8
Classifier: Programming Language :: Python :: 3.9
Classifier: Operating System :: OS Independent
Requires-Python: >=3.7
Requires-Dist: psycopg2-binary
Requires-Dist: mysql-connector-python
Requires-Dist: pymongo
Requires-Dist: pymongo[srv]
Requires-Dist: dnspython
Requires-Dist: ensure
Requires-Dist: pytest ==7.1.3
Requires-Dist: tox
Requires-Dist: black ==22.8.0
Requires-Dist: flake8 ==5.0.4
Requires-Dist: mypy ==0.971
Provides-Extra: testing
Requires-Dist: pytest >=7.1.3 ; extra == 'testing'
Requires-Dist: mypy >=0.971 ; extra == 'testing'
Requires-Dist: flake8 >=5.0.4 ; extra == 'testing'
Requires-Dist: tox >=3.25.1 ; extra == 'testing'
Requires-Dist: black >=22.8.0 ; extra == 'testing'
